dvid/__init__.py
dvid/config.py
dvid/decode.py
dvid/fetch.py
dvid/meshing.py
dvid/tip.py
dvid/utils.py
dvidtools-0.5.0.dist-info/LICENSE
dvidtools-0.5.0.dist-info/METADATA
dvidtools-0.5.0.dist-info/WHEEL
dvidtools-0.5.0.dist-info/top_level.txt
dvidtools-0.5.0.dist-info/RECORD
