Metadata-Version: 2.1
Name: dvidtools
Version: 0.5.0
Summary: Fetch data from DVID server
Home-page: https://github.com/flyconnectome/dvid_tools
Author: Philipp Schlegel
Author-email: pms70@cam.ac.uk
License: GNU GPL V3
Project-URL: Documentation, https://dvidtools.readthedocs.io
Project-URL: Source, https://github.com/flyconnectome/dvid_tools
Keywords: DVID API fetch neuron segmentation
Classifier: Development Status :: 4 - Beta
Classifier: Intended Audience :: Science/Research
Classifier: Topic :: Scientific/Engineering :: Bio-Informatics
Classifier: License :: OSI Approved :: GNU General Public License v3 or later (GPLv3+)
Classifier: Programming Language :: Python :: 3
Classifier: Programming Language :: Python :: 3.8
Classifier: Programming Language :: Python :: 3.9
Classifier: Programming Language :: Python :: 3.10
Classifier: Programming Language :: Python :: 3.11
Requires-Python: >=3.8
License-File: LICENSE
Requires-Dist: numpy >=1.15.3
Requires-Dist: pandas >=0.23.4
Requires-Dist: setuptools >=40.5.0
Requires-Dist: tqdm >=4.28.1
Requires-Dist: scikit-image >=0.14.1
Requires-Dist: scipy
Requires-Dist: requests
Requires-Dist: trimesh
Requires-Dist: networkx
Provides-Extra: extras
Requires-Dist: scikit-learn ==0.20.3 ; extra == 'extras'
